django_private_chat/__init__.py
django_private_chat/admin.py
django_private_chat/apps.py
django_private_chat/channels.py
django_private_chat/channels_uvloop.py
django_private_chat/handlers.py
django_private_chat/models.py
django_private_chat/router.py
django_private_chat/urls.py
django_private_chat/utils.py
django_private_chat/views.py
django_private_chat/management/__init__.py
django_private_chat/management/commands/__init__.py
django_private_chat/management/commands/run_chat_server.py
django_private_chat/management/commands/run_chat_server_uvloop.py
django_private_chat/migrations/0001_initial.py
django_private_chat/migrations/0002_message_read.py
django_private_chat/migrations/__init__.py
django_private_chat/static/django_private_chat/css/django_private_chat.css
django_private_chat/static/django_private_chat/js/django_private_chat.js
django_private_chat/templates/django_private_chat/base.html
django_private_chat/templates/django_private_chat/dialogs.html
django_private_chat-0.2.2.dist-info/DESCRIPTION.rst
django_private_chat-0.2.2.dist-info/METADATA
django_private_chat-0.2.2.dist-info/RECORD
django_private_chat-0.2.2.dist-info/WHEEL
django_private_chat-0.2.2.dist-info/metadata.json
django_private_chat-0.2.2.dist-info/top_level.txt
