Metadata-Version: 1.1
Name: django-private-chat
Version: 0.2.2
Summary: Django one-to-one Websocket-based Asyncio-handled chat, developed by Bearle team
Home-page: https://github.com/Bearle/django-private-chat
Author: Bearle
Author-email: tech@bearle.ru
License: ISCL
Keywords: django-private-chat
Platform: UNKNOWN
Classifier: Development Status :: 3 - Alpha
Classifier: Framework :: Django
Classifier: Framework :: Django :: 1.8
Classifier: Framework :: Django :: 1.9
Classifier: Framework :: Django :: 1.10
Classifier: Intended Audience :: Developers
Classifier: License :: OSI Approved :: ISC License (ISCL)
Classifier: Natural Language :: English
Classifier: Programming Language :: Python :: 3.4
Classifier: Programming Language :: Python :: 3.5
Classifier: Programming Language :: Python :: 3.6
